{"total_results": 8087, "kind": "search#companies", "page_number": 4, "items": [{"company_number": "04666183", "address_snippet": "34 Ashburnham Road, Ampthill, Bedford, England, MK45 2RH", "matches": {"snippet": []}, "title": "ALICE WELLS DESIGN LIMITED", "company_type": "ltd", "links": {"self": "/company/04666183"}, "company_status": "active", "address": {"country": "England", "address_line_2": "Ampthill", "postal_code": "MK45 2RH", "address_line_1": "34 Ashburnham Road", "locality": "Bedford"}, "snippet": "", "description_identifier": ["incorporated-on"], "kind": "searchresults#company", "description": "04666183 - Incorporated on 13 February 2003", "date_of_creation": "2003-02-13"}, {"date_of_cessation": "2024-08-27", "company_type": "ltd", "title": "ALISON WELLS NUTRITION LTD", "links": {"self": "/company/12640134"}, "address_snippet": "Flat 38 Wildcroft Manor, Wildcroft Road, London, England, SW15 3TT", "matches": {"snippet": []}, "company_status": "dissolved", "company_number": "12640134", "date_of_creation": "2020-06-02", "description": "12640134 - Dissolved on 27 August 2024", "kind": "searchresults#company", "description_identifier": ["dissolved-on"], "snippet": "", "address": {"locality": "London", "address_line_1": "Flat 38 Wildcroft Manor", "postal_code": "SW15 3TT", "address_line_2": "Wildcroft Road", "country": "England"}}, {"company_number": "14202524", "matches": {"snippet": []}, "address_snippet": "91 Allison Street, Digbeth, Birmingham, England, B5 5TH", "links": {"self": "/company/14202524"}, "company_type": "ltd", "title": "ALLISON WELLS SOLICITORS LTD", "company_status": "active", "snippet": "", "address": {"address_line_2": "Digbeth", "country": "England", "premises": "91", "address_line_1": "Allison Street", "postal_code": "B5 5TH", "locality": "Birmingham"}, "description_identifier": ["incorporated-on"], "kind": "searchresults#company", "date_of_creation": "2022-06-29", "description": "14202524 - Incorporated on 29 June 2022"}, {"description_identifier": ["dissolved-on"], "snippet": "", "address": {"region": "Angus", "premises": "9", "locality": "Arbroath", "postal_code": "DD11 4HT", "address_line_1": "Hercules Place"}, "date_of_creation": "2012-07-18", "description": "SC428590 - Dissolved on 30 January 2024", "kind": "searchresults#company", "company_number": "SC428590", "date_of_cessation": "2024-01-30", "company_type": "ltd", "links": {"self": "/company/SC428590"}, "title": "ALLT WELLSERVICES LIMITED", "address_snippet": "9 Hercules Place, Arbroath, Angus, DD11 4HT", "matches": {"snippet": []}, "company_status": "dissolved"}, {"company_number": "14031865", "company_status": "active", "title": "ALL WELLS AND GOOD LIMITED", "company_type": "ltd", "links": {"self": "/company/14031865"}, "address_snippet": "C/O Ocelot Accounting, 54 Parkstone Road, Poole, Dorset, England, BH15 2PG", "matches": {"snippet": []}, "description_identifier": ["incorporated-on"], "address": {"postal_code": "BH15 2PG", "address_line_1": "54 Parkstone Road", "locality": "Poole", "region": "Dorset", "country": "England", "premises": "C/O Ocelot Accounting"}, "snippet": "", "description": "14031865 - Incorporated on  7 April 2022", "date_of_creation": "2022-04-07", "kind": "searchresults#company"}, {"snippet": "", "address": {"region": "Kent", "locality": "Tunbridge Wells", "postal_code": "TN2 5HT", "address_line_1": "227 Forest Road"}, "description_identifier": ["incorporated-on"], "kind": "searchresults#company", "description": "05977646 - Incorporated on 25 October 2006", "date_of_creation": "2006-10-25", "company_number": "05977646", "company_status": "active", "address_snippet": "227 Forest Road, Tunbridge Wells, Kent, TN2 5HT", "matches": {"snippet": []}, "company_type": "private-limited-guarant-nsc", "title": "AMBERLEY (TUNBRIDGE WELLS) LIMITED", "links": {"self": "/company/05977646"}}, {"kind": "searchresults#company", "date_of_creation": "2012-08-02", "description": "SC429557 - Incorporated on  2 August 2012", "snippet": "", "address": {"region": "Angus", "locality": "Montrose", "address_line_1": "182 High Street", "postal_code": "DD10 8PH"}, "description_identifier": ["incorporated-on"], "company_status": "active", "matches": {"snippet": []}, "address_snippet": "182 High Street, Montrose, Angus, DD10 8PH", "company_type": "ltd", "title": "AMM WELLS LIMITED", "links": {"self": "/company/SC429557"}, "company_number": "SC429557"}, {"address_snippet": "4 Chesterfield Road Chesterfield Road, Eckington, Sheffield, England, S21 4BD", "matches": {"snippet": []}, "company_type": "ltd", "links": {"self": "/company/09844771"}, "title": "AM WELLS PROPERTY LIMITED", "company_status": "active", "company_number": "09844771", "kind": "searchresults#company", "date_of_creation": "2015-10-27", "description": "09844771 - Incorporated on 27 October 2015", "snippet": "", "address": {"locality": "Sheffield", "address_line_1": "4 Chesterfield Road Chesterfield Road", "postal_code": "S21 4BD", "address_line_2": "Eckington", "country": "England"}, "description_identifier": ["incorporated-on"]}, {"description_identifier": ["incorporated-on"], "snippet": "", "address": {"postal_code": "LE17 5AS", "address_line_1": "Unit 1, Gables Farm Frolesworth Lane", "locality": "Leicestershire", "address_line_2": "Claybrooke Magna", "country": "United Kingdom"}, "description": "13057492 - Incorporated on  2 December 2020", "date_of_creation": "2020-12-02", "kind": "searchresults#company", "company_number": "13057492", "company_type": "ltd", "links": {"self": "/company/13057492"}, "title": "ANDERSON WELLS PROPERTY LIMITED", "matches": {"snippet": []}, "address_snippet": "Unit 1, Gables Farm Frolesworth Lane, Claybrooke Magna, Leicestershire, United Kingdom, LE17 5AS", "company_status": "active"}, {"address_snippet": "139-141 Watling Street, Gillingham, Kent, ME7 2YY", "matches": {"snippet": []}, "company_type": "ltd", "title": "ANDREW WELLS ARCHITECTURAL PLANNING & DESIGN LTD", "links": {"self": "/company/08190184"}, "company_status": "active", "company_number": "08190184", "kind": "searchresults#company", "description": "08190184 - Incorporated on 23 August 2012", "date_of_creation": "2012-08-23", "address": {"region": "Kent", "postal_code": "ME7 2YY", "address_line_1": "139-141 Watling Street", "locality": "Gillingham"}, "snippet": "", "description_identifier": ["incorporated-on"]}], "start_index": 30, "items_per_page": 10}