{"page_number": 63, "items_per_page": 10, "items": [{"address_snippet": "Parkgates Bury New Road, Prestwich, Manchester, M25 0JW", "address": {"address_line_1": "Prestwich", "postal_code": "M25 0JW", "premises": "Parkgates Bury New Road", "locality": "Manchester"}, "date_of_cessation": "2016-01-26", "date_of_creation": "2011-08-03", "company_number": "07728313", "description_identifier": ["dissolved-on"], "description": "07728313 - Dissolved on 26 January 2016", "company_status": "dissolved", "company_type": "ltd", "kind": "searchresults#company", "title": "UK PAINT DEPOT LIMITED", "links": {"self": "/company/07728313"}}, {"title": "UK PANSCAPE ARCHITECTURE DESIGN CO., LTD", "company_type": "ltd", "kind": "searchresults#company", "links": {"self": "/company/08570123"}, "description": "08570123 - Dissolved on 26 January 2016", "description_identifier": ["dissolved-on"], "date_of_creation": "2013-06-14", "company_number": "08570123", "company_status": "dissolved", "date_of_cessation": "2016-01-26", "address_snippet": "Chase Business Centre, 39-41 Chase Side, London, N14 5BP", "address": {"locality": "London", "premises": "Chase Business Centre", "postal_code": "N14 5BP", "address_line_1": "39-41 Chase Side"}}, {"date_of_cessation": "2016-01-12", "address_snippet": "Sibson Airfield, Wansford, Peterborough, Cambridgeshire, PE8 6NE", "address": {"address_line_1": "Wansford", "region": "Cambridgeshire", "premises": "Sibson Airfield", "postal_code": "PE8 6NE", "locality": "Peterborough"}, "kind": "searchresults#company", "company_type": "private-limited-guarant-nsc", "title": "UK PARACHUTING CLUB LTD", "links": {"self": "/company/08880359"}, "company_number": "08880359", "date_of_creation": "2014-02-06", "description": "08880359 - Dissolved on 12 January 2016", "description_identifier": ["dissolved-on"], "company_status": "dissolved"}, {"date_of_cessation": "2022-02-01", "address_snippet": "4 Charles Close, Seaford, England, BN25 2TR", "address": {"address_line_1": "Charles Close", "premises": "4", "country": "England", "postal_code": "BN25 2TR", "locality": "Seaford"}, "kind": "searchresults#company", "company_type": "ltd", "title": "CHILDRENS PARTY IN A BOX LTD", "links": {"self": "/company/09766541"}, "date_of_creation": "2015-09-08", "company_number": "09766541", "description_identifier": ["dissolved-on"], "description": "09766541 - Dissolved on  1 February 2022", "company_status": "dissolved"}, {"address_snippet": "First Floor, 41 Chalton Street, London, United Kingdom, NW1 1JD", "address": {"address_line_1": "41 Chalton Street", "premises": "First Floor", "postal_code": "NW1 1JD", "country": "United Kingdom", "locality": "London"}, "date_of_cessation": "2015-12-15", "description": "08199389 - Dissolved on 15 December 2015", "description_identifier": ["dissolved-on"], "company_number": "08199389", "date_of_creation": "2012-09-03", "company_status": "dissolved", "title": "UK PANGTE AUTOMOBILE REPACKING LIMITED", "kind": "searchresults#company", "company_type": "ltd", "links": {"self": "/company/08199389"}}, {"description": "08950069 - Dissolved on  3 November 2015", "description_identifier": ["dissolved-on"], "company_number": "08950069", "date_of_creation": "2014-03-20", "company_status": "dissolved", "title": "UK PASVO INTERNATIONAL HOLDING LIMITED", "kind": "searchresults#company", "company_type": "ltd", "links": {"self": "/company/08950069"}, "address_snippet": "Chase Business Centre, 39-41 Chase Side, London, England, N14 5BP", "address": {"address_line_1": "39-41 Chase Side", "country": "England", "postal_code": "N14 5BP", "premises": "Chase Business Centre", "locality": "London"}, "date_of_cessation": "2015-11-03"}, {"address": {"region": "Shropshire", "premises": "10 ", "postal_code": "SY1 3AF", "address_line_2": "Battlefield Enterprise Park", "address_line_1": "Park Plaza", "locality": "Shrewsbury"}, "address_snippet": "10  Park Plaza, Battlefield Enterprise Park, Shrewsbury, Shropshire, SY1 3AF", "date_of_cessation": "2015-11-03", "company_status": "dissolved", "company_number": "08336118", "date_of_creation": "2012-12-19", "description": "08336118 - Dissolved on  3 November 2015", "description_identifier": ["dissolved-on"], "links": {"self": "/company/08336118"}, "kind": "searchresults#company", "company_type": "ltd", "title": "UK PAT LTD"}, {"company_number": "04000658", "date_of_creation": "2000-05-24", "description": "04000658 - Dissolved on  6 October 2015", "description_identifier": ["dissolved-on"], "company_status": "dissolved", "kind": "searchresults#company", "company_type": "ltd", "title": "UK PACIFIC PARTNERS LIMITED", "links": {"self": "/company/04000658"}, "address_snippet": "6  St. Andrew Street, London, EC4A 3AE", "address": {"locality": "London", "premises": "6 ", "postal_code": "EC4A 3AE", "address_line_1": "St. Andrew Street"}, "date_of_cessation": "2015-10-06"}, {"address_snippet": "Uk Sameday Childerplay Road, Off Tunstall Road, Stoke On Trent, ST8 7PZ", "address": {"postal_code": "ST8 7PZ", "premises": "Uk Sameday Childerplay Road", "address_line_1": "Off Tunstall Road", "locality": "Stoke On Trent"}, "date_of_cessation": "2015-10-06", "description_identifier": ["dissolved-on"], "description": "08896475 - Dissolved on  6 October 2015", "company_number": "08896475", "date_of_creation": "2014-02-14", "company_status": "dissolved", "title": "UK PATROL SECURITY LIMITED", "kind": "searchresults#company", "company_type": "ltd", "links": {"self": "/company/08896475"}}, {"date_of_cessation": "2015-09-15", "address": {"address_line_1": "Bradley Road", "postal_code": "LL13 7TG", "premises": "49 ", "locality": "Wrexham"}, "address_snippet": "49  Bradley Road, Wrexham, LL13 7TG", "links": {"self": "/company/08376991"}, "title": "UK PARKING MARSHALS LTD", "kind": "searchresults#company", "company_type": "ltd", "company_status": "dissolved", "description_identifier": ["dissolved-on"], "description": "08376991 - Dissolved on 15 September 2015", "company_number": "08376991", "date_of_creation": "2013-01-28"}], "total_results": 716, "start_index": 620, "kind": "search#companies"}