{"items": [{"kind": "searchresults#company", "address_snippet": "63/66 63/66 Hatton Garden,, Fifth Floor Suite 23,, London, England, EC1N 8LE", "description_identifier": ["incorporated-on"], "company_number": "12083744", "title": "VANGUARD UK PROPERTIES LTD", "description": "12083744 - Incorporated on  3 July 2019", "date_of_creation": "2019-07-03", "company_status": "active", "links": {"self": "/company/12083744"}, "company_type": "ltd", "address": {"premises": "63/66", "address_line_2": "Fifth Floor Suite 23,", "locality": "London", "address_line_1": "63/66 Hatton Garden,", "postal_code": "EC1N 8LE", "country": "England"}}], "items_per_page": 10, "kind": "search#companies", "start_index": 0, "page_number": 1, "total_results": 1}