{"total_results": 8087, "kind": "search#companies", "start_index": 500, "items_per_page": 10, "page_number": 51, "items": [{"date_of_creation": "1994-04-28", "company_status": "active", "address": {"locality": "Cardiff", "region": "South Glamorgan", "postal_code": "CF14 4UH", "address_line_1": "Cresswell House", "address_line_2": "Field Way"}, "snippet": "", "address_snippet": "Cresswell House, Field Way, Cardiff, South Glamorgan, CF14 4UH", "kind": "searchresults#company", "description_identifier": ["incorporated-on"], "title": "KNOX & WELLS HOLDINGS LIMITED", "company_type": "ltd", "matches": {"snippet": []}, "description": "02924037 - Incorporated on 28 April 1994", "links": {"self": "/company/02924037"}, "company_number": "02924037"}, {"address": {"region": "Oxon", "postal_code": "OX2 9NU", "locality": "Oxford", "address_line_1": "Mayfield House Lower Whitley Road", "address_line_2": "Filchampstead", "country": "England"}, "kind": "searchresults#company", "address_snippet": "Mayfield House Lower Whitley Road, Filchampstead, Oxford, Oxon, England, OX2 9NU", "snippet": "KNOX WELLS HOLDINGS LTD ", "date_of_creation": "2021-02-12", "company_status": "active", "matches": {"snippet": []}, "company_type": "ltd", "title": "KNOX - WELLS ENTERPRISES LTD", "company_number": "13198336", "description": "13198336 - Incorporated on 12 February 2021", "links": {"self": "/company/13198336"}, "description_identifier": ["incorporated-on"]}, {"description_identifier": ["dissolved-on"], "description": "14446704 - Dissolved on 17 December 2024", "links": {"self": "/company/14446704"}, "company_number": "14446704", "title": "K.R. WELLSERVICE LIMITED", "company_type": "ltd", "date_of_cessation": "2024-12-17", "matches": {"snippet": []}, "company_status": "dissolved", "date_of_creation": "2022-10-27", "address_snippet": "4385, 14446704 - COMPANIES HOUSE DEFAULT ADDRESS, Cardiff, CF14 8LH", "snippet": "", "kind": "searchresults#company", "address": {"locality": "Cardiff", "postal_code": "CF14 8LH", "address_line_1": "14446704 - COMPANIES HOUSE DEFAULT ADDRESS", "po_box": "4385"}}, {"description_identifier": ["incorporated-on"], "matches": {"snippet": []}, "title": "KT WELLS LIMITED", "company_type": "ltd", "company_number": "09333429", "description": "09333429 - Incorporated on  1 December 2014", "links": {"self": "/company/09333429"}, "date_of_creation": "2014-12-01", "company_status": "active", "address": {"country": "England", "address_line_2": "Winnersh", "address_line_1": "100 Berkshire Place Wharfedale Road", "locality": "Wokingham", "postal_code": "RG41 5RD"}, "kind": "searchresults#company", "address_snippet": "100 Berkshire Place Wharfedale Road, Winnersh, Wokingham, England, RG41 5RD", "snippet": ""}, {"description_identifier": ["incorporated-on"], "company_number": "08396451", "links": {"self": "/company/08396451"}, "description": "08396451 - Incorporated on 11 February 2013", "matches": {"snippet": []}, "company_type": "ltd", "title": "K2 (WELLS) LIMITED", "company_status": "active", "date_of_creation": "2013-02-11", "kind": "searchresults#company", "snippet": "", "address_snippet": "Bishopbrook House, Cathedral Avenue, Wells, Somerset, BA5 1FD", "address": {"locality": "Wells", "region": "Somerset", "postal_code": "BA5 1FD", "address_line_2": "Cathedral Avenue", "address_line_1": "Bishopbrook House"}}, {"company_status": "active", "date_of_creation": "2024-08-06", "kind": "searchresults#company", "address_snippet": "22 Tyersal Park, Bradford, England, BD4 8EY", "snippet": "", "address": {"address_line_1": "22 Tyersal Park", "country": "England", "postal_code": "BD4 8EY", "locality": "Bradford"}, "description_identifier": ["incorporated-on"], "company_number": "15880752", "description": "15880752 - Incorporated on  6 August 2024", "links": {"self": "/company/15880752"}, "matches": {"snippet": []}, "company_type": "ltd", "title": "LAC WELLS LIMITED"}, {"date_of_creation": "2014-01-27", "company_status": "active", "address": {"locality": "Newark", "postal_code": "NG24 1AX", "address_line_1": "Ossington Chambers", "address_line_2": "6-8 Castle Gate", "country": "England"}, "kind": "searchresults#company", "snippet": "MATT WELLS LIMITED ", "address_snippet": "Ossington Chambers, 6-8 Castle Gate, Newark, England, NG24 1AX", "description_identifier": ["incorporated-on"], "matches": {"snippet": []}, "title": "LAGAN FILMS LTD", "company_type": "ltd", "company_number": "08863004", "links": {"self": "/company/08863004"}, "description": "08863004 - Incorporated on 27 January 2014"}, {"description": "12317612 - Incorporated on 15 November 2019", "links": {"self": "/company/12317612"}, "company_number": "12317612", "company_type": "ltd", "title": "LAITH AND WELLS LTD", "matches": {"snippet": []}, "description_identifier": ["incorporated-on"], "address_snippet": "39 Mill Way, Bushey, England, WD23 2AF", "snippet": "", "kind": "searchresults#company", "address": {"postal_code": "WD23 2AF", "locality": "Bushey", "address_line_1": "39 Mill Way", "country": "England"}, "company_status": "active", "date_of_creation": "2019-11-15"}, {"kind": "searchresults#company", "snippet": "", "address_snippet": "140/141  Temple Chambers, Temple Avenue, London Ec4y Ohe", "address": {"premises": "140/141 ", "address_line_2": "Temple Avenue", "address_line_1": "Temple Chambers", "locality": "London Ec4y Ohe"}, "company_status": "liquidation", "date_of_creation": "1978-06-06", "company_number": "01372129", "description": "01372129 - Incorporated on  6 June 1978 - Liquidation", "links": {"self": "/company/01372129"}, "matches": {"snippet": []}, "title": "LANBOURNE WELLS LIMITED", "company_type": "ltd", "description_identifier": ["incorporated-on", "liquidation"]}, {"description_identifier": ["incorporated-on"], "links": {"self": "/company/09614136"}, "description": "09614136 - Incorporated on 29 May 2015", "company_number": "09614136", "company_type": "ltd", "title": "LANCASTER ROBERTS UK LTD", "matches": {"snippet": []}, "company_status": "active", "date_of_creation": "2015-05-29", "address_snippet": "35 Strathmore Drive, Baildon, Shipley, England, BD17 5LP", "snippet": "MORGAN WELLS UK LTD ", "kind": "searchresults#company", "address": {"locality": "Shipley", "postal_code": "BD17 5LP", "country": "England", "address_line_1": "35 Strathmore Drive", "address_line_2": "Baildon"}}]}